<?xml version="1.0"?>
<users>
    
    <user>
        <name>Jane Smith</name>
        <age>42</age>
    </user>
    <user>
        <name>Michael Johnson</name>
        <age>42</age>
    </user>
    <user>
        <name>lolko</name>
        <age>15</age>
    </user>
    <user>
        <name>lolko</name>
        <age>15</age>
    </user>
    <user>
        <name>lolko</name>
        <age>15</age>
    </user>
    <user id="1689939785">
        <name>majo</name>
    </user>
    <user id="1689939902">
        <name>majo</name>
    </user>
    <user id="1689940022">
        <name>majo</name>
    </user>
    <user id="1689940027">
        <name>majo</name>
    </user>
    <user id="1689944198">
        <name>majo</name>
    </user>
    <user id="1689944201">
        <name>majo</name>
    </user>
    <user id="1689944327">
        <name>majo</name>
    </user>
    <user id="1689944458">
        <name>majo</name>
        <age>45</age>
    </user>
    <user id="1689944464">
        <name>majo</name>
    </user>
    <user id="1689944723">
        <name>majo</name>
        <age>100</age>
    </user>
    <user id="1689944757">
        <name>majo</name>
        <age>1</age>
    </user>
    <user id="1689953056">
        <name>majko</name>
        <age>15</age>
    </user>
    <user id="1690012358">
        <name>majko</name>
        <age>100</age>
    </user>
    <user id="1690017520">
        <name>majko</name>
        <age>100</age>
    </user>
<user id="1690019861"><name>majko</name><age>15</age></user><user id="1690020249"><name>majkooo</name><age>10</age></user></users>
